{
  "SceneObj_Activity_Common_Property_Ani_Prop_CodeMachine_01": {
    "$type": "ConfigGadget",
    "common": {
      "disableTickDistance": 100000
    },
    "globalValue": {
      "serverGlobalValues": [
        "SGV_Increase_Val",
        "SGV_Fixing",
        "SGV_Notify_Val"
      ],
      "initServerGlobalValues": {
        "SGV_Increase_Val": 0,
        "SGV_Fixing": 0,
        "SGV_Notify_Val": 0
      }
    },
    "hasModel": true,
    "combat": {
      "property": {
        "HP": 99999,
        "weight": 50,
        "isLockHP": true,
        "isGhostToAllied": true,
        "isGhostToEnemy": true
      },
      "beHit": {
        "hitBloodEffect": "",
        "hitAutoRedirect": false,
        "muteAllHitText": true
      },
      "combatLock": {
        "lockShape": "CircleLockEnemy",
        "denyLockOn": true,
        "lockType": "Gadget_Lv1"
      }
    },
    "combatTemplate": "",
    "abilities": [
      {
        "abilityID": "SceneObj_Activity_Common_Property_Ani_Prop_CodeMachine_01",
        "abilityName": "SceneObj_Activity_Common_Property_Ani_Prop_CodeMachine_01",
        "abilityOverride": ""
      }
    ],
    "field": {
      "concernType": "AllAvatars",
      "shape": "CircleR1.5H3",
      "fromShape": "",
      "triggerInfinite": true,
      "lifeInfinite": true,
      "checkInterval": 0.2,
      "overwriteCampType": true,
      "campType": "All",
      "colliderName": "",
      "fromColliderName": ""
    },
    "radarHint": true,
    "billboard": {
      "$type": "EIBMPIAMKNN",
      "attachPoint": "RootNode",
      "offset": {
        "y": 2
      },
      "radiusOffset": 1,
      "showDistance": 99,
      "showHPBar": true,
      "size": "Grand"
    },
    "forceSetEntityType": "Gadget"
  },
  "SceneObj_Activity_Common_Property_Ani_Prop_Prison_01": {
    "$type": "ConfigGadget",
    "common": {
      "disableTickDistance": 1000000
    },
    "hasModel": true,
    "combat": {
      "property": {
        "HP": 1000,
        "attack": 100,
        "weight": 50,
        "isLockHP": true,
        "isGhostToAllied": true,
        "isGhostToEnemy": true
      },
      "beHit": {
        "hitBloodEffect": "",
        "hitAutoRedirect": false,
        "muteAllHitEffect": true,
        "muteAllHitText": true
      },
      "combatLock": {
        "lockShape": "CircleLockEnemy",
        "denyLockOn": true,
        "lockType": "Gadget_Lv1"
      },
      "die": {
        "dieForceDisappearTime": 0,
        "dieDisappearEffect": ""
      }
    },
    "combatTemplate": "",
    "abilities": [
      {
        "abilityID": "SceneObj_Activity_Common_Property_Ani_Prop_Prison_01",
        "abilityName": "SceneObj_Activity_Common_Property_Ani_Prop_Prison_01",
        "abilityOverride": ""
      }
    ],
    "field": {
      "concernType": "AllAvatars",
      "shape": "CircleR1.5H3",
      "fromShape": "",
      "triggerInfinite": true,
      "lifeInfinite": true,
      "checkInterval": 0.2,
      "overwriteCampType": true,
      "campType": "All",
      "colliderName": "",
      "fromColliderName": ""
    },
    "move": {
      "$type": "ConfigPlatformMove",
      "avatarTriggerEventDistance": 3.2
    },
    "forceSetEntityType": "Gadget"
  }
}
