{
  "Lisa_Constellation_1": [
    {
      "DNBCBBHMELG": "All",
      "talentParam": "Lisa_ThunderFall_Talent_ReviveElemEnergy",
      "abilityName": "Avatar_Lisa_ThunderFall",
      "PJPMKAKJHKE": true,
      "$type": "UnlockTalentParam"
    }
  ],
  "Lisa_Constellation_2": [
    {
      "DNBCBBHMELG": "All",
      "talentParam": "Lisa_Constellation_2",
      "abilityName": "Avatar_Lisa_ThunderFall",
      "PJPMKAKJHKE": true,
      "$type": "UnlockTalentParam"
    }
  ],
  "Lisa_Constellation_3": [
    {
      "DNBCBBHMELG": "All",
      "extraLevel": 3,
      "talentType": "AvatarSkill",
      "talentIndex": 9,
      "PJPMKAKJHKE": true,
      "$type": "AddTalentExtraLevel"
    }
  ],
  "Lisa_Constellation_4": [
    {
      "DNBCBBHMELG": "All",
      "paramSpecial": "_Ball_Attack_COUNT_RANGE",
      "paramDelta": 2,
      "abilityName": "Avatar_Lisa_PierceLightning_Ball_Attack",
      "paramRatio": 0,
      "PJPMKAKJHKE": true,
      "$type": "ModifyAbility"
    }
  ],
  "Lisa_Constellation_5": [
    {
      "DNBCBBHMELG": "All",
      "extraLevel": 3,
      "talentType": "AvatarSkill",
      "talentIndex": 2,
      "PJPMKAKJHKE": true,
      "$type": "AddTalentExtraLevel"
    }
  ],
  "Lisa_Constellation_6": [
    {
      "DNBCBBHMELG": "All",
      "talentParam": "Lisa_Constellation_6",
      "abilityName": "Avatar_Lisa_StaticElecField",
      "PJPMKAKJHKE": true,
      "$type": "UnlockTalentParam"
    }
  ],
  "Lisa_PermanentSkill_1": [
    {
      "DNBCBBHMELG": "All",
      "talentParam": "Lisa_ExtraAttack_StaticElecField",
      "abilityName": "Avatar_Lisa_StaticElecField",
      "PJPMKAKJHKE": true,
      "$type": "UnlockTalentParam"
    }
  ],
  "Lisa_PermanentSkill_2": [
    {
      "DNBCBBHMELG": "All",
      "talentParam": "Lisa_Constellation_5",
      "abilityName": "Avatar_Lisa_PierceLightning_Ball_Attack",
      "PJPMKAKJHKE": true,
      "$type": "UnlockTalentParam"
    }
  ],
  "Lisa_SkillUpgrade_1": [
    {
      "DNBCBBHMELG": "All",
      "talentParam": "Magic_TriStars",
      "abilityName": "Avatar_Lisa_Attack01",
      "PJPMKAKJHKE": true,
      "$type": "UnlockTalentParam"
    },
    {
      "DNBCBBHMELG": "All",
      "talentParam": "Magic_TriStars",
      "abilityName": "Avatar_Lisa_Attack02",
      "PJPMKAKJHKE": true,
      "$type": "UnlockTalentParam"
    },
    {
      "DNBCBBHMELG": "All",
      "talentParam": "Magic_TriStars",
      "abilityName": "Avatar_Lisa_Attack03",
      "PJPMKAKJHKE": true,
      "$type": "UnlockTalentParam"
    },
    {
      "DNBCBBHMELG": "All",
      "talentParam": "Magic_TriStars",
      "abilityName": "Avatar_Lisa_Attack04",
      "PJPMKAKJHKE": true,
      "$type": "UnlockTalentParam"
    },
    {
      "DNBCBBHMELG": "All",
      "paramSpecial": "Damage01",
      "paramDelta": "%1",
      "abilityName": "Avatar_Lisa_Attack01",
      "paramRatio": 0,
      "PJPMKAKJHKE": true,
      "$type": "ModifyAbility"
    },
    {
      "DNBCBBHMELG": "All",
      "paramSpecial": "Damage02",
      "paramDelta": "%2",
      "abilityName": "Avatar_Lisa_Attack02",
      "paramRatio": 0,
      "PJPMKAKJHKE": true,
      "$type": "ModifyAbility"
    },
    {
      "DNBCBBHMELG": "All",
      "paramSpecial": "Damage03",
      "paramDelta": "%3",
      "abilityName": "Avatar_Lisa_Attack03",
      "paramRatio": 0,
      "PJPMKAKJHKE": true,
      "$type": "ModifyAbility"
    },
    {
      "DNBCBBHMELG": "All",
      "paramSpecial": "Damage04",
      "paramDelta": "%4",
      "abilityName": "Avatar_Lisa_Attack04",
      "paramRatio": 0,
      "PJPMKAKJHKE": true,
      "$type": "ModifyAbility"
    },
    {
      "DNBCBBHMELG": "All",
      "paramSpecial": "Lisa_ExtraAttack_Damage",
      "paramDelta": "%5",
      "abilityName": "Avatar_Lisa_ExtraAttack_Damage",
      "paramRatio": 0,
      "PJPMKAKJHKE": true,
      "$type": "ModifyAbility"
    },
    {
      "DNBCBBHMELG": "All",
      "paramSpecial": "ExtraAttack_Catalyst_Stamina_Cost",
      "paramDelta": "%6",
      "abilityName": "Avatar_Lisa_ExtraAttack",
      "paramRatio": 0,
      "PJPMKAKJHKE": true,
      "$type": "ModifyAbility"
    },
    {
      "DNBCBBHMELG": "All",
      "paramSpecial": "FallingAnthem_Normal_Loop_Damage",
      "paramDelta": "%7",
      "abilityName": "Avatar_Lisa_FallingAnthem",
      "PJPMKAKJHKE": true,
      "$type": "ModifyAbility"
    },
    {
      "DNBCBBHMELG": "All",
      "paramSpecial": "FallingAnthem_Normal_Rank_1_Damage",
      "paramDelta": "%8",
      "abilityName": "Avatar_Lisa_FallingAnthem",
      "PJPMKAKJHKE": true,
      "$type": "ModifyAbility"
    },
    {
      "DNBCBBHMELG": "All",
      "paramSpecial": "FallingAnthem_Normal_Rank_2_Damage",
      "paramDelta": "%9",
      "abilityName": "Avatar_Lisa_FallingAnthem",
      "PJPMKAKJHKE": true,
      "$type": "ModifyAbility"
    }
  ],
  "Lisa_SkillUpgrade_2": [
    {
      "DNBCBBHMELG": "All",
      "paramSpecial": "Damage_0",
      "paramDelta": "%1",
      "abilityName": "Avatar_Lisa_ThunderFall",
      "paramRatio": 0,
      "PJPMKAKJHKE": true,
      "$type": "ModifyAbility"
    },
    {
      "DNBCBBHMELG": "All",
      "paramSpecial": "Damage_1",
      "paramDelta": "%2",
      "abilityName": "Avatar_Lisa_ThunderFall",
      "paramRatio": 0,
      "PJPMKAKJHKE": true,
      "$type": "ModifyAbility"
    },
    {
      "DNBCBBHMELG": "All",
      "paramSpecial": "Damage_2",
      "paramDelta": "%3",
      "abilityName": "Avatar_Lisa_ThunderFall",
      "paramRatio": 0,
      "PJPMKAKJHKE": true,
      "$type": "ModifyAbility"
    },
    {
      "DNBCBBHMELG": "All",
      "paramSpecial": "Damage_3",
      "paramDelta": "%4",
      "abilityName": "Avatar_Lisa_ThunderFall",
      "paramRatio": 0,
      "PJPMKAKJHKE": true,
      "$type": "ModifyAbility"
    },
    {
      "DNBCBBHMELG": "All",
      "paramSpecial": "Damage",
      "paramDelta": "%6",
      "abilityName": "Avatar_Lisa_FlickerWaveDamage",
      "paramRatio": 0,
      "PJPMKAKJHKE": true,
      "$type": "ModifyAbility"
    }
  ],
  "Lisa_SkillUpgrade_3": [
    {
      "DNBCBBHMELG": "All",
      "paramSpecial": "Damage",
      "paramDelta": "%1",
      "abilityName": "Avatar_Lisa_PierceLightning_Ball_Attack",
      "paramRatio": 0,
      "PJPMKAKJHKE": true,
      "$type": "ModifyAbility"
    }
  ]
}
