{
  "FauneAbyssale_Aplysia_Larva_Bubble": {
    "$type": "ConfigGadget",
    "common": {
      "effectAttachShape": {
        "$type": "ConfigEffectAttachBox",
        "MDDGMBKHHEG": 0.5,
        "KFCBGJGELGH": 0.5,
        "OGNCHCNHLAO": 0.5
      }
    },
    "combat": {
      "property": {
        "useCreatorProperty": true,
        "isInvincible": true,
        "isGhostToEnemy": true,
        "canTriggerBullet": false
      },
      "combatLock": {
        "lockShape": "CircleLockEnemy",
        "denyLockOn": true,
        "lockType": "Default"
      }
    },
    "combatTemplate": "",
    "abilities": [
      {
        "abilityID": "",
        "abilityName": "FauneAbyssale_Aplysia_Larva_BubbleBullet",
        "abilityOverride": ""
      },
      {
        "abilityID": "",
        "abilityName": "FauneAbyssale_Aplysia_Larva_BubbleBullet_LifeTimeOverVFX",
        "abilityOverride": ""
      }
    ],
    "timer": {
      "lifeTime": 5
    },
    "move": {
      "$type": "ConfigItanoCircusBulletMove",
      "speed": 8.6,
      "minSpeed": 6,
      "JBDLDPMPBNN": 40,
      "NBIPGPBHPCC": 0,
      "DFFLBAEENFC": {
        "$type": "BDKHNGDHLBP"
      },
      "PMAJIGHCBEO": 40,
      "CNMBCDMCLJP": 0.9
    },
    "gadget": {
      "$type": "ConfigBulletPattern",
      "collision": {
        "targetType": "Enemy",
        "ignoreWater": true
      },
      "triggerActions": [
        {
          "$type": "ConfigGadgetTriggerAbility",
          "abilityName": "FauneAbyssale_Aplysia_Larva_BubbleBullet"
        }
      ],
      "triggerLifeOverActions": [
        {
          "$type": "ConfigGadgetTriggerAbility",
          "abilityName": "FauneAbyssale_Aplysia_Larva_BubbleBullet_LifeTimeOverVFX"
        }
      ]
    }
  },
  "FauneAbyssale_Aplysia_Larva_Frolic_Bubble": {
    "$type": "ConfigGadget",
    "common": {
      "effectAttachShape": {
        "$type": "ConfigEffectAttachBox",
        "MDDGMBKHHEG": 0.5,
        "KFCBGJGELGH": 0.5,
        "OGNCHCNHLAO": 0.5
      }
    },
    "combat": {
      "property": {
        "useCreatorProperty": true,
        "isInvincible": true,
        "isGhostToEnemy": true,
        "canTriggerBullet": false
      },
      "combatLock": {
        "lockShape": "CircleLockEnemy",
        "denyLockOn": true,
        "lockType": "Default"
      }
    },
    "combatTemplate": "",
    "abilities": [
      {
        "abilityID": "",
        "abilityName": "FauneAbyssale_Aplysia_Larva_FrolicBubble",
        "abilityOverride": ""
      }
    ],
    "timer": {
      "lifeTime": 5
    },
    "move": {
      "$type": "ConfigItanoCircusBulletMove",
      "speed": 9,
      "minSpeed": 6,
      "JBDLDPMPBNN": 2,
      "NBIPGPBHPCC": 0,
      "DFFLBAEENFC": {
        "$type": "BDKHNGDHLBP"
      },
      "PMAJIGHCBEO": 2,
      "CNMBCDMCLJP": 0.7
    },
    "gadget": {
      "$type": "ConfigBulletPattern",
      "collision": {
        "targetType": "AllExceptSelf",
        "ignoreWater": true,
        "bornWithTriggerEnabled": false
      },
      "colliderCheckOnInit": false,
      "triggerActions": [
        {
          "$type": "ConfigGadgetTriggerAbility",
          "abilityName": "FauneAbyssale_Aplysia_Larva_FrolicBubble"
        }
      ],
      "triggerLifeOverActions": [
        {
          "$type": "ConfigGadgetTriggerAbility",
          "abilityName": "FauneAbyssale_Aplysia_Larva_FrolicBubble"
        }
      ],
      "AHCHIHHNLEF": 0.222,
      "CBPMAPDNDLJ": true
    }
  },
  "FauneAbyssale_Aplysia_Mature_IceBullet": {
    "$type": "ConfigGadget",
    "common": {
      "effectAttachShape": {
        "$type": "ConfigEffectAttachBox",
        "MDDGMBKHHEG": 0.5,
        "KFCBGJGELGH": 0.5,
        "OGNCHCNHLAO": 0.5
      }
    },
    "combat": {
      "property": {
        "useCreatorProperty": true,
        "isInvincible": true,
        "isGhostToEnemy": true,
        "canTriggerBullet": false
      },
      "combatLock": {
        "lockShape": "CircleLockEnemy",
        "denyLockOn": true,
        "lockType": "Default"
      }
    },
    "combatTemplate": "",
    "abilities": [
      {
        "abilityID": "",
        "abilityName": "FauneAbyssale_Aplysia_Mature_IceBullet",
        "abilityOverride": ""
      },
      {
        "abilityID": "",
        "abilityName": "FauneAbyssale_Aplysia_Mature_IceBullet_LifeTimeOverVFX",
        "abilityOverride": ""
      }
    ],
    "timer": {
      "lifeTime": 3
    },
    "move": {
      "$type": "ConfigItanoCircusBulletMove",
      "speed": 11,
      "minSpeed": 3,
      "JBDLDPMPBNN": 81,
      "AOHCALMCNHB": 2,
      "NBIPGPBHPCC": 0.5,
      "DFFLBAEENFC": {
        "$type": "BDKHNGDHLBP"
      },
      "PMAJIGHCBEO": 81,
      "CNMBCDMCLJP": 1
    },
    "gadget": {
      "$type": "ConfigBulletPattern",
      "collision": {
        "targetType": "Enemy"
      },
      "triggerActions": [
        {
          "$type": "ConfigGadgetTriggerAbility",
          "abilityName": "FauneAbyssale_Aplysia_Mature_IceBullet"
        }
      ],
      "triggerLifeOverActions": [
        {
          "$type": "ConfigGadgetTriggerAbility",
          "abilityName": "FauneAbyssale_Aplysia_Mature_IceBullet_LifeTimeOverVFX"
        }
      ]
    }
  },
  "FauneAbyssale_Aplysia_Mature_WaterBullet": {
    "$type": "ConfigGadget",
    "common": {
      "effectAttachShape": {
        "$type": "ConfigEffectAttachBox",
        "MDDGMBKHHEG": 0.5,
        "KFCBGJGELGH": 0.5,
        "OGNCHCNHLAO": 0.5
      }
    },
    "combat": {
      "property": {
        "useCreatorProperty": true,
        "isInvincible": true,
        "isGhostToEnemy": true,
        "canTriggerBullet": false
      },
      "combatLock": {
        "lockShape": "CircleLockEnemy",
        "denyLockOn": true,
        "lockType": "Default"
      }
    },
    "combatTemplate": "",
    "abilities": [
      {
        "abilityID": "",
        "abilityName": "FauneAbyssale_Aplysia_Mature_WaterBullet",
        "abilityOverride": ""
      },
      {
        "abilityID": "",
        "abilityName": "FauneAbyssale_Aplysia_Mature_WaterBullet_LifeTimeOverVFX",
        "abilityOverride": ""
      }
    ],
    "timer": {
      "lifeTime": 5
    },
    "move": {
      "$type": "ConfigItanoCircusBulletMove",
      "speed": 8,
      "minSpeed": 3,
      "JBDLDPMPBNN": 80,
      "AOHCALMCNHB": 2,
      "NBIPGPBHPCC": 0.5,
      "DFFLBAEENFC": {
        "$type": "BDKHNGDHLBP"
      },
      "PMAJIGHCBEO": 80,
      "CNMBCDMCLJP": 0.3
    },
    "gadget": {
      "$type": "ConfigBulletPattern",
      "collision": {
        "targetType": "Enemy",
        "ignoreWater": true
      },
      "triggerActions": [
        {
          "$type": "ConfigGadgetTriggerAbility",
          "abilityName": "FauneAbyssale_Aplysia_Mature_WaterBullet"
        }
      ],
      "triggerLifeOverActions": [
        {
          "$type": "ConfigGadgetTriggerAbility",
          "abilityName": "FauneAbyssale_Aplysia_Mature_WaterBullet_LifeTimeOverVFX"
        }
      ]
    }
  },
  "FauneAbyssale_Aplysia_Mature_IcedJellyBlast_Dummy": {
    "$type": "ConfigGadget",
    "combat": {
      "property": {
        "useCreatorProperty": true,
        "isInvincible": true,
        "isGhostToEnemy": true,
        "canTriggerBullet": false
      },
      "combatLock": {
        "lockShape": "CircleLockEnemy",
        "denyLockOn": true,
        "lockType": "Default"
      }
    },
    "combatTemplate": "",
    "abilities": [
      {
        "abilityID": "",
        "abilityName": "FauneAbyssale_Aplysia_Mature_IcedJellyBlast_DummyGadget",
        "abilityOverride": ""
      }
    ],
    "timer": {
      "lifeTime": 1
    }
  },
  "FauneAbyssale_Aplysia_Mature_Jelly": {
    "$type": "ConfigGadget",
    "combat": {
      "property": {
        "useCreatorProperty": true,
        "isLockHP": true
      },
      "beHit": {
        "hitBloodEffect": "",
        "muteAllHitEffect": true,
        "muteAllHitText": true
      },
      "combatLock": {
        "lockShape": "CircleLockEnemy",
        "lockType": "Boss_Lv5"
      }
    },
    "combatTemplate": "",
    "timer": {
      "lifeInfinite": true
    },
    "move": {
      "$type": "ConfigFollowMove",
      "target": "TargetEntity",
      "attachPoint": "JellyGadget",
      "followRotation": true,
      "NDKPBDKKOKB": ""
    },
    "billboard": {
      "$type": "MELDONMDGPK",
      "attachPoint": "BillboardAttach",
      "BNIHJMEOOKA": "Character",
      "MEAELOBIJGG": 0.5,
      "FCGJHIODAAK": true,
      "showDistance": 32,
      "IIOJGNIMJHM": true,
      "APONJHADNHL": 24,
      "OGFAAPGPGAE": true
    }
  }
}
